wmtile/__init__.py
wmtile/__main__.py
wmtile/desktops/wmtile-b.desktop
wmtile/desktops/wmtile-c.desktop
wmtile/desktops/wmtile-l.desktop
wmtile/desktops/wmtile-m.desktop
wmtile/desktops/wmtile-p.desktop
wmtile/desktops/wmtile-s.desktop
wmtile/desktops/wmtile-t.desktop
wmtile/docs/WMTile 1.0.1 User Manual.pdf
wmtile/icons/wmtile-b.ico
wmtile/icons/wmtile-c.ico
wmtile/icons/wmtile-l.ico
wmtile/icons/wmtile-m.ico
wmtile/icons/wmtile-p.ico
wmtile/icons/wmtile-s.ico
wmtile/icons/wmtile-t.ico
wmtile-1.0.1.dist-info/entry_points.txt
wmtile-1.0.1.dist-info/WHEEL
wmtile-1.0.1.dist-info/METADATA
wmtile-1.0.1.dist-info/RECORD
