Metadata-Version: 2.1
Name: wmtile
Version: 1.0.1
Summary: WMTile - a window tiler for XFCE desktop environment
Author-email: Carlo Alessandro Verre <carlo.alessandro.verre@gmail.com>
Requires-Python: >=3.6
Classifier: Programming Language :: Python :: 3
Classifier: Programming Language :: Python :: 3.6
Classifier: Development Status :: 5 - Production/Stable
Classifier: Environment :: Console
Classifier: Intended Audience :: End Users/Desktop
Classifier: License :: OSI Approved :: GNU General Public License v3 or later (GPLv3+)
Classifier: Operating System :: POSIX :: Linux
Project-URL: Home, https://pypi.org/project/wmtile
